personal_tracker/__init__.py
personal_tracker/helpers.py
personal_tracker/kalman_filter.py
personal_tracker/personal_tracker.py
personal_tracker/detector/__init__.py
personal_tracker/detector/detector.py
personal_tracker/detector/detector_result.py
personal_tracker/embedder/__init__.py
personal_tracker/embedder/available_embedder_models.py
personal_tracker/embedder/clip_embedder.py
personal_tracker/embedder/emebedder.py
personal_tracker/metric/__init__.py
personal_tracker/metric/cosine_similarity.py
personal_tracker/metric/cosine_similarity2.py
personal_tracker/metric/csem.py
personal_tracker/metric/euclidian.py
personal_tracker/metric/mahalanobis.py
personal_tracker/metric/metric.py
personal_tracker/metric/metric_type.py
personal_tracker/models/__init__.py
personal_tracker/models/osnet.py
personal_tracker/models/osnet_ain.py
personal_tracker/tracker/__init__.py
personal_tracker/tracker/track_result.py
personal_tracker/tracker/tracker.py
personal_tracker/tracker/tracker_config.py
validates/__init__.py
validates/main.py
personal_tracker-0.0.3.dist-info/METADATA
personal_tracker-0.0.3.dist-info/WHEEL
personal_tracker-0.0.3.dist-info/top_level.txt
personal_tracker-0.0.3.dist-info/RECORD
